oneary/__init__.py
oneary/__main__.py
oneary/config.py
oneary/logger.py
oneary/oneary.py
oneary/utils.py
oneary/webhooks.py
oneary-1.0.0.dist-info/LICENSE
oneary-1.0.0.dist-info/METADATA
oneary-1.0.0.dist-info/WHEEL
oneary-1.0.0.dist-info/entry_points.txt
oneary-1.0.0.dist-info/RECORD
